jupyter_functions_exec-0.4.0.dist-info/METADATA
jupyter_functions_exec-0.4.0.dist-info/WHEEL
jupyter_functions_exec-0.4.0.dist-info/licenses/LICENSE
jupyter_functions_exec/__init__.py
jupyter_functions_exec/jupyter_functions_exec.cpython-314-x86_64-linux-gnu.so
jupyter_functions_exec-0.4.0.dist-info/RECORD
