Metadata-Version: 2.4
Name: jupyter_functions_exec
Version: 0.4.0
License-File: LICENSE
Summary: Clase rápida para trabajar con notebooks
Author-email: Oscar <oscarortegarios@gmail.com>
License: MIT
